python_brtools/__init__.py
python_brtools/__main__.py
python_brtools/brtools.py
python_brtools/cli.py
python_brtools/py.typed
python_brtools-0.0.2.dist-info/LICENSE
python_brtools-0.0.2.dist-info/WHEEL
python_brtools-0.0.2.dist-info/METADATA
python_brtools-0.0.2.dist-info/RECORD
