Metadata-Version: 2.1
Name: python-brtools
Version: 0.0.2
Summary: Validate CPF and CNPJ
Home-page: https://github.com/drummerzzz/pypi_brtools/README.md
License: MIT
Keywords: cpf,cnpj,validador,validação,validation,validator,poetry
Author: Drummerzzz
Author-email: devdrummerzzz@gmail.com
Requires-Python: >=3.8,<4.0
Classifier: License :: OSI Approved :: MIT License
Classifier: Programming Language :: Python :: 3
Classifier: Programming Language :: Python :: 3.8
Classifier: Programming Language :: Python :: 3.9
Requires-Dist: validate-cnpj (>=0.0.1,<0.0.2)
Requires-Dist: validate-cpf (>=0.1.2,<0.2.0)
Project-URL: Repository, https://github.com/drummerzzz/pypi_brtools
